pecoret_default_templates/__init__.py
pecoret_default_templates/vulnerability_templates/categories.yaml
pecoret_default_templates/vulnerability_templates/_template/info.yaml
pecoret_default_templates/vulnerability_templates/_template/locale/de/description.md
pecoret_default_templates/vulnerability_templates/_template/locale/de/recommendation.md
pecoret_default_templates/vulnerability_templates/_template/locale/en/description.md
pecoret_default_templates/vulnerability_templates/_template/locale/en/recommendation.md
pecoret_default_templates/vulnerability_templates/broken-access-control/info.yaml
pecoret_default_templates/vulnerability_templates/broken-access-control/locale/de/description.md
pecoret_default_templates/vulnerability_templates/broken-access-control/locale/de/recommendation.md
pecoret_default_templates/vulnerability_templates/broken-access-control/locale/en/description.md
pecoret_default_templates/vulnerability_templates/broken-access-control/locale/en/recommendation.md
pecoret_default_templates/vulnerability_templates/cert-long-lifespan/info.yaml
pecoret_default_templates/vulnerability_templates/cert-long-lifespan/locale/de/description.md
pecoret_default_templates/vulnerability_templates/cert-long-lifespan/locale/de/recommendation.md
pecoret_default_templates/vulnerability_templates/cert-long-lifespan/locale/en/description.md
pecoret_default_templates/vulnerability_templates/cert-long-lifespan/locale/en/recommendation.md
pecoret_default_templates/vulnerability_templates/cookie-httponly-flag/info.yaml
pecoret_default_templates/vulnerability_templates/cookie-httponly-flag/locale/de/description.md
pecoret_default_templates/vulnerability_templates/cookie-httponly-flag/locale/de/recommendation.md
pecoret_default_templates/vulnerability_templates/cookie-httponly-flag/locale/en/description.md
pecoret_default_templates/vulnerability_templates/cookie-httponly-flag/locale/en/recommendation.md
pecoret_default_templates-0.0.1.dist-info/METADATA
pecoret_default_templates-0.0.1.dist-info/WHEEL
pecoret_default_templates-0.0.1.dist-info/top_level.txt
pecoret_default_templates-0.0.1.dist-info/RECORD
