Metadata-Version: 2.1
Name: pecoret-default-templates
Version: 0.0.1
Summary: PeCoReT default templates.
Home-page: https://github.com/PeCoReT/default_templates
Author: peco21
Author-email: 
